mona_client/__init__.py
mona_client/client.py
mona_client/logger.py
mona_client/mona_configuration.py
mona_client/mona_thread.py
mona_client/certs/root.pem
mona_client/config/mona_client_config.json
mona_client-0.2.7.dist-info/LICENSE
mona_client-0.2.7.dist-info/METADATA
mona_client-0.2.7.dist-info/WHEEL
mona_client-0.2.7.dist-info/top_level.txt
mona_client-0.2.7.dist-info/RECORD
