Metadata-Version: 2.1
Name: mona-client
Version: 0.2.7
Summary: Client code for python Mona instrumentation
Home-page: https://gitlab.com/mona-labs/mona-python-client
Author: MonaLabs
Author-email: itai@monalabs.io
License: UNKNOWN
Download-URL: http://pypi.python.org/pypi/mona-client/
Platform: UNKNOWN
Classifier: Programming Language :: Python :: 3
Classifier: License :: OSI Approved :: Apache Software License
Classifier: Operating System :: OS Independent
Requires-Dist: mona-fluent-logger (>=0.0.5)
Requires-Dist: watchdog (>=0.9.0)
Requires-Dist: werkzeug (>=0.14)
